shablbot/__init__.py
shablbot/__main__.py
shablbot/shablbot.py
shablbot/components/__init__.py
shablbot/components/chat.py
shablbot/components/command.py
shablbot/components/event_handler.py
shablbot/components/keyboard.py
shablbot/components/module.py
shablbot/components/phrases.py
shablbot/components/user.py
shablbot/components/handlers/__init__.py
shablbot/components/handlers/command.py
shablbot/components/handlers/message.py
shablbot/components/handlers/modules.py
shablbot/components/handlers/models/__init__.py
shablbot/components/handlers/models/message_models.py
shablbot/core/__init__.py
shablbot/core/color.py
shablbot/core/exceptions.py
shablbot/core/manager_commands.py
shablbot/core/utils.py
shablbot/init/__init__.py
shablbot/init/commands/__init__.py
shablbot/init/commands/private/__init__.py
shablbot/init/commands/private/show_id_active_chats.py
shablbot/init/commands/public/__init__.py
shablbot/init/commands/public/chat_bot_off.py
shablbot/init/commands/public/chat_bot_on.py
shablbot/init/commands/public/chat_show_statistics.py
shablbot/init/keyboards/__init__.py
shablbot/init/keyboards/clear.json
shablbot/init/keyboards/default.json
shablbot/init/modules/__init__.py
shablbot/init/modules/games/__init__.py
shablbot/init/modules/games/flip_and_roll.py
shablbot/init/phrases/__init__.py
shablbot/init/phrases/_default.json
shablbot/init/phrases/bye.json
shablbot/init/phrases/hello.json
shablbot/init/settings/__init__.py
shablbot/init/settings/settings.py
shablbot/init/settings/settings_model.py
shablbot/models/__init__.py
shablbot/models/chat.py
shablbot/models/command.py
shablbot/models/event_handler.py
shablbot/models/module.py
shablbot/models/phrases.py
shablbot/models/shablbot.py
shablbot/settings/__init__.py
shablbot/settings/settings_model.py
shablbot-2.0.4.dist-info/LICENSE
shablbot-2.0.4.dist-info/METADATA
shablbot-2.0.4.dist-info/WHEEL
shablbot-2.0.4.dist-info/top_level.txt
shablbot-2.0.4.dist-info/RECORD
