Metadata-Version: 2.1
Name: shablbot
Version: 2.0.4
Summary: Бот написанный на Python для социальной сети Вконтакте, работающий через VkBotLongPull
Home-page: https://github.com/Blackgard/shablbot
Download-URL: https://github.com/Blackgard/shablbot/tarball/v2.0.4
Author: Alexandr Drachenin
Author-email: alexdrachenin98@gmail.com
License: MIT
Keywords: python,bot,vk,template
Requires-Python: >=3.8
License-File: LICENSE
Requires-Dist: vk-api (==11.9.4)
Requires-Dist: requests (==2.26.0)
Requires-Dist: pytz (==2021.1)
Requires-Dist: loguru (==0.5.3)
Requires-Dist: python-dotenv (==0.19.0)
Requires-Dist: pydantic (==1.8.2)
Requires-Dist: anytree (==2.8.0)
Requires-Dist: certifi (==2021.10.8)
Requires-Dist: charset-normalizer (==2.0.7)
Requires-Dist: colorama (==0.4.4)
Requires-Dist: idna (==3.3)
Requires-Dist: six (==1.16.0)
Requires-Dist: urllib3 (==1.26.7)
Requires-Dist: win32-setctime (==1.0.3)
